croco/demo.py
croco/pretrain.py
croco/models/blocks.py
croco/models/criterion.py
croco/models/croco.py
croco/models/croco_downstream.py
croco/models/dpt_block.py
croco/models/head_downstream.py
croco/models/masking.py
croco/models/pos_embed.py
croco/models/curope/__init__.py
croco/models/curope/curope.cp310-win_amd64.pyd
croco/models/curope/curope2d.py
croco/models/curope/setup.py
croco/utils/misc.py
depth_anything_v2/dinov2.py
depth_anything_v2/dpt.py
depth_anything_v2/dinov2_layers/__init__.py
depth_anything_v2/dinov2_layers/attention.py
depth_anything_v2/dinov2_layers/block.py
depth_anything_v2/dinov2_layers/drop_path.py
depth_anything_v2/dinov2_layers/layer_scale.py
depth_anything_v2/dinov2_layers/mlp.py
depth_anything_v2/dinov2_layers/patch_embed.py
depth_anything_v2/dinov2_layers/swiglu_ffn.py
depth_anything_v2/util/blocks.py
depth_anything_v2/util/transform.py
dust3r/__init__.py
dust3r/demo.py
dust3r/image_pairs.py
dust3r/inference.py
dust3r/losses.py
dust3r/model.py
dust3r/optim_factory.py
dust3r/patch_embed.py
dust3r/post_process.py
dust3r/training.py
dust3r/viz.py
dust3r/cloud_opt/__init__.py
dust3r/cloud_opt/base_opt.py
dust3r/cloud_opt/commons.py
dust3r/cloud_opt/init_im_poses.py
dust3r/cloud_opt/modular_optimizer.py
dust3r/cloud_opt/optimizer.py
dust3r/cloud_opt/pair_viewer.py
dust3r/datasets/__init__.py
dust3r/datasets/arkitscenes.py
dust3r/datasets/blendedmvs.py
dust3r/datasets/co3d.py
dust3r/datasets/habitat.py
dust3r/datasets/megadepth.py
dust3r/datasets/scannetpp.py
dust3r/datasets/staticthings3d.py
dust3r/datasets/waymo.py
dust3r/datasets/wildrgbd.py
dust3r/datasets/base/__init__.py
dust3r/datasets/base/base_stereo_view_dataset.py
dust3r/datasets/base/batched_sampler.py
dust3r/datasets/base/easy_dataset.py
dust3r/datasets/utils/__init__.py
dust3r/datasets/utils/cropping.py
dust3r/datasets/utils/transforms.py
dust3r/dust3r/__init__.py
dust3r/heads/__init__.py
dust3r/heads/dpt_head.py
dust3r/heads/linear_head.py
dust3r/heads/postprocess.py
instantsplat-1.8.4.dist-info/licenses/LICENSE
instantsplat-1.8.4.dist-info/METADATA
instantsplat-1.8.4.dist-info/WHEEL
instantsplat-1.8.4.dist-info/top_level.txt
instantsplat-1.8.4.dist-info/RECORD
