Metadata-Version: 2.4
Name: instantsplat
Version: 1.8.4
Summary: Refactored python initialization and training code for InstantSplat
Home-page: https://github.com/yindaheng98/instantsplat
Author: yindaheng98
Author-email: yindaheng98@gmail.com
License-File: LICENSE
Requires-Dist: gaussian-splatting
Requires-Dist: scipy
Requires-Dist: huggingface_hub
Requires-Dist: einops
Requires-Dist: roma
Requires-Dist: scikit-learn
Dynamic: author
Dynamic: author-email
Dynamic: description
Dynamic: description-content-type
Dynamic: home-page
Dynamic: license-file
Dynamic: requires-dist
Dynamic: summary
